{
  "@context": "https://schema.org",
  "@type": "Recipe",
  "name": "Garlic Pepper Salmon Belly",
  "image": [
    "https://healthyfied.me/images/recipes/garlic-pepper-salmon-belly.jpg"
  ],
  "author": {
    "@type": "Organization",
    "name": "Healthyfied"
  },
  "publisher": {
    "@type": "Organization",
    "name": "Healthyfied",
    "logo": {
      "@type": "ImageObject",
      "url": "https://healthyfied.me/logo.jpg"
    }
  },
  "datePublished": "2025-03-09",
  "description": "Indulge in the flavors of the sea with this Garlic Pepper Salmon Belly recipe. Perfect for those following a low-carb and low-sugar diet, this dish is not only healthy but also packed with the goodness of omega-3 fatty acids. Elevate your mealtime with a recipe that prioritizes your health without compromising on taste.",
  "prepTime": "PT10M",
  "cookTime": "PT8M",
  "totalTime": "PT18M",
  "keywords": "low-carb,high-sodium,low-sugar,Healthyfied,Healthy Recipes,Healthified Recipes",
  "recipeYield": "3",
  "recipeCategory": "Low Carb",
  "recipeCuisine": "Filipino",
  "cookingMethod": "Cooking",
  "nutrition": {
    "@type": "NutritionInformation",
    "calories": "636",
    "carbohydrateContent": "1",
    "fiberContent": "0",
    "sugarContent": "0",
    "sodiumContent": "722",
    "proteinContent": "17",
    "fatContent": "57",
    "saturatedFatContent": "12",
    "monounsaturatedFatContent": "0",
    "polyunsaturatedFatContent": "0",
    "unsaturatedFatContent": 0,
    "transFatContent": "0"
  },
  "recipeIngredient": [
    "0.25  teaspoon Salt",
    "1  tsp ground, Pepper",
    "5 g Garlic, raw",
    "500 g Belly"
  ],
  "recipeInstructions": [
    {
      "@type": "HowToStep",
      "text": "Prep the ingredients: Mince the garlic and season the salmon belly with salt and ground pepper on all sides.",
      "name": "Step 1"
    },
    {
      "@type": "HowToStep",
      "text": "Preheat a non-stick skillet over medium-high heat.",
      "name": "Step 2"
    },
    {
      "@type": "HowToStep",
      "text": "Cook the salmon belly, skin-side down first, for about 3-4 minutes until the skin is crispy.",
      "name": "Step 3"
    },
    {
      "@type": "HowToStep",
      "text": "Flip the salmon and add the minced garlic to the skillet, cooking for an additional 3-4 minutes until the salmon is golden and cooked through.",
      "name": "Step 4"
    }
  ],
  "suitableForDiet": []
}